covid19poland/PLgov.py
covid19poland/PLstat.py
covid19poland/PLtwitter.py
covid19poland/PLwiki.py
covid19poland/__init__.py
covid19poland/export.py
covid19poland/offline.py
covid19poland/parse.py
covid19poland/data/2020-03.json
covid19poland/data/2020-04.json
covid19poland/data/2020-05.json
covid19poland/data/2020-06.json
covid19poland/data/2020-07.json
covid19poland/data/2020-08.json
covid19poland/data/2020-09.json
covid19poland/data/2020-10.json
covid19poland/data/2020-11.json
covid19poland/data/NUTS_PL.csv
covid19poland/data/deaths.csv
covid19poland/data/unknown.json
covid19poland-0.9.0.dist-info/LICENSE
covid19poland-0.9.0.dist-info/METADATA
covid19poland-0.9.0.dist-info/WHEEL
covid19poland-0.9.0.dist-info/top_level.txt
covid19poland-0.9.0.dist-info/RECORD
