Metadata-Version: 2.1
Name: covid19poland
Version: 0.9.0
Summary: Web Scraper for Poland COVID19 data.
Home-page: https://github.com/martinbenes1996/covid19poland
Author: Martin Beneš
Author-email: martinbenes1996@gmail.com
License: MIT
Download-URL: https://github.com/martinbenes1996/covid19poland/archive/0.9.0.tar.gz
Keywords: 2019-nCov,poland,coronavirus,covid-19,covid-data,covid19-data
Platform: UNKNOWN
Classifier: Development Status :: 4 - Beta
Classifier: Intended Audience :: Science/Research
Classifier: Intended Audience :: Developers
Classifier: Intended Audience :: Other Audience
Classifier: Topic :: Database
Classifier: Topic :: Scientific/Engineering
Classifier: Topic :: Scientific/Engineering :: Information Analysis
Classifier: Topic :: Software Development :: Libraries
Classifier: Topic :: Utilities
Classifier: License :: OSI Approved :: Mozilla Public License 2.0 (MPL 2.0)
Classifier: Programming Language :: Python :: 3
Classifier: Programming Language :: Python :: 3.4
Classifier: Programming Language :: Python :: 3.5
Classifier: Programming Language :: Python :: 3.6
Requires-Dist: beautifulsoup4
Requires-Dist: GetOldTweets3
Requires-Dist: openpyxl
Requires-Dist: pandas
Requires-Dist: requests
Requires-Dist: xlrd
Requires-Dist: waybackmachine
Requires-Dist: covid19dh
Requires-Dist: pytz
